MTM/NMS.py
MTM/__init__.py
MTM/version.py
Multi_Template_Matching-2.0.1.dist-info/LICENSE
Multi_Template_Matching-2.0.1.dist-info/METADATA
Multi_Template_Matching-2.0.1.dist-info/WHEEL
Multi_Template_Matching-2.0.1.dist-info/top_level.txt
Multi_Template_Matching-2.0.1.dist-info/RECORD
