Metadata-Version: 2.1
Name: Multi-Template-Matching
Version: 2.0.1
Summary: Object-recognition in images using multiple templates
Home-page: https://github.com/multi-template-matching/MultiTemplateMatching-Python
Author: Laurent Thomas
Author-email: laurent132.thomas@laposte.net
Keywords: object-recognition object-localization
Classifier: Programming Language :: Python :: 3
Classifier: License :: OSI Approved :: MIT License
Classifier: Operating System :: OS Independent
Classifier: Topic :: Scientific/Engineering :: Image Recognition
Classifier: Intended Audience :: Science/Research
License-File: LICENSE
Requires-Dist: numpy>=1.21
Requires-Dist: opencv-python-headless>=4.5.4
Requires-Dist: scikit-image
Requires-Dist: scipy
